LICENSE
MANIFEST.in
README.md
setup.py
jdAptDirReinstall/__init__.py
jdAptDirReinstall/jdAptDirReinstall.py
jdAptDirReinstall.egg-info/PKG-INFO
jdAptDirReinstall.egg-info/SOURCES.txt
jdAptDirReinstall.egg-info/dependency_links.txt
jdAptDirReinstall.egg-info/entry_points.txt
jdAptDirReinstall.egg-info/top_level.txt